data_selection/__init__.py
data_selection/base.py
data_selection/hashed_ngram_dsir.py
data_selection/utils.py
data_selection-1.0.3.dist-info/LICENSE
data_selection-1.0.3.dist-info/METADATA
data_selection-1.0.3.dist-info/WHEEL
data_selection-1.0.3.dist-info/top_level.txt
data_selection-1.0.3.dist-info/RECORD
