Metadata-Version: 2.1
Name: data-selection
Version: 1.0.3
Summary: Data Selection with Importance Resampling
Home-page: https://github.com/p-lambda/dsir
Author: Sang Michael Xie
Author-email: Sang Michael Xie <xie@cs.stanford.edu>
License: MIT License
Project-URL: Homepage, https://github.com/p-lambda/dsir
Keywords: data selection,importance resampling,dsir,nlp,language models
Classifier: Programming Language :: Python :: 3
Classifier: License :: OSI Approved :: MIT License
Classifier: Operating System :: OS Independent
Requires-Python: >=3.6
License-File: LICENSE
Requires-Dist: numpy >=1.21.6
Requires-Dist: tqdm >=4.62.3
Requires-Dist: joblib >=1.1.0
Requires-Dist: nltk >=3.8.1
Provides-Extra: dev
Requires-Dist: pytest ; extra == 'dev'
